README.md
setup.py
gymail/__init__.py
gymail/core.py
gymail.egg-info/PKG-INFO
gymail.egg-info/SOURCES.txt
gymail.egg-info/dependency_links.txt
gymail.egg-info/entry_points.txt
gymail.egg-info/requires.txt
gymail.egg-info/top_level.txt