Metadata-Version: 1.0
Name: gymail
Version: 0.2.8
Summary: gymail wraps around smptlib and MIMEMultipart to send either warning, error or info mails to a recipient, using html and css to markup and format the email appropriately, thus gymail can be used to send email notifications from scripts.
Home-page: https://github.com/eayin2/gymail
Author: eayin2
Author-email: eayin2@gmail.com
License: UNKNOWN
Platform: UNKNOWN
